<?xml version="1.0" encoding="utf-8"?>
<doctrine-mapping xmlns="http://doctrine-project.org/schemas/orm/doctrine-mapping" xmlns:xsi="http://www.w3.org/2001/XMLSchema-instance" xsi:schemaLocation="http://doctrine-project.org/schemas/orm/doctrine-mapping http://doctrine-project.org/schemas/orm/doctrine-mapping.xsd">
  <entity name="Icsoc\SecurityBundle\Entity\CcAdmins" table="cc_admins" repository-class="Icsoc\SecurityBundle\Entity\CcAdminsRepository">
    <indexes>
      <index name="agent_status" columns="agent_status"/>
    </indexes>
    <id name="id" type="integer" column="id">
      <generator strategy="IDENTITY"/>
    </id>
    <field name="agentGrade" type="boolean" column="agent_grade" nullable="false"/>
    <field name="agentAccount" type="string" column="agent_account" length="30" nullable="false"/>
    <field name="companyName" type="string" column="company_name" length="50" nullable="false"/>
    <field name="account" type="string" column="account" length="20" nullable="false"/>
    <field name="password" type="string" column="password" length="32" nullable="false"/>
    <field name="superiorAgent" type="integer" column="superior_agent" nullable="false"/>
    <field name="agentStatus" type="boolean" column="agent_status" nullable="false"/>
    <field name="province" type="integer" column="province" nullable="false"/>
    <field name="city" type="integer" column="city" nullable="false"/>
    <field name="county" type="integer" column="county" nullable="false"/>
    <field name="address" type="string" column="address" length="100" nullable="false"/>
    <field name="represention" type="string" column="represention" length="20" nullable="false"/>
    <field name="contactPhone" type="string" column="contact_phone" length="20" nullable="false"/>
    <field name="contactor" type="string" column="contactor" length="20" nullable="false"/>
    <field name="officePhone" type="string" column="office_phone" length="20" nullable="false"/>
    <field name="mobilePhone" type="string" column="mobile_phone" length="20" nullable="false"/>
    <field name="fax" type="string" column="fax" length="20" nullable="false"/>
    <field name="postCode" type="string" column="post_code" length="6" nullable="false"/>
    <field name="email" type="string" column="email" length="50" nullable="false"/>
    <field name="aptitude1" type="boolean" column="aptitude1" nullable="false"/>
    <field name="aptitude2" type="boolean" column="aptitude2" nullable="false"/>
    <field name="aptitude3" type="boolean" column="aptitude3" nullable="false"/>
    <field name="aptitude4" type="boolean" column="aptitude4" nullable="false"/>
    <field name="addTime" type="integer" column="add_time" nullable="false"/>
    <field name="localType" type="boolean" column="local_type" nullable="false"/>
    <field name="localPreMinutes" type="boolean" column="local_pre_minutes" nullable="false"/>
    <field name="localPreFee" type="decimal" column="local_pre_fee" precision="10" scale="3" nullable="false"/>
    <field name="remark" type="string" column="remark" length="250" nullable="false"/>
    <field name="localAfterRate" type="decimal" column="local_after_rate" precision="10" scale="3" nullable="false"/>
    <field name="localRate" type="decimal" column="local_rate" precision="10" scale="3" nullable="false"/>
    <field name="longRate" type="decimal" column="long_rate" precision="10" scale="3" nullable="false"/>
    <field name="longType" type="boolean" column="long_type" nullable="false"/>
    <field name="longPreMinutes" type="boolean" column="long_pre_minutes" nullable="false"/>
    <field name="longPreFee" type="decimal" column="long_pre_fee" precision="10" scale="3" nullable="false"/>
    <field name="longAfterRate" type="decimal" column="long_after_rate" precision="10" scale="3" nullable="false"/>
    <field name="specialRate" type="decimal" column="special_rate" precision="10" scale="3" nullable="false"/>
    <field name="specialType" type="boolean" column="special_type" nullable="false"/>
    <field name="specialPreMinutes" type="boolean" column="special_pre_minutes" nullable="false"/>
    <field name="specialPreFee" type="decimal" column="special_pre_fee" precision="10" scale="3" nullable="false"/>
    <field name="specialAfterRate" type="decimal" column="special_after_rate" precision="10" scale="3" nullable="false"/>
    <field name="phoneMonthly" type="decimal" column="phone_monthly" precision="10" scale="2" nullable="false"/>
    <field name="agentMonthly" type="decimal" column="agent_monthly" precision="10" scale="2" nullable="false"/>
    <field name="trunkMonthly" type="decimal" column="trunk_monthly" precision="10" scale="2" nullable="false"/>
    <field name="lastLogin" type="integer" column="last_login" nullable="false"/>
    <field name="lastIp" type="string" column="last_ip" length="15" nullable="false"/>
    <field name="actionList" type="text" column="action_list" length="65535" nullable="false"/>
    <field name="systemAdmin" type="boolean" column="system_admin" nullable="false"/>
  </entity>
</doctrine-mapping>
